odoo/addons/easy_my_coop_recompute_coop_number/__init__.py
odoo/addons/easy_my_coop_recompute_coop_number/__manifest__.py
odoo/addons/easy_my_coop_recompute_coop_number/wizard/__init__.py
odoo/addons/easy_my_coop_recompute_coop_number/wizard/cooperator_number_wizard.py
odoo/addons/easy_my_coop_recompute_coop_number/wizard/cooperator_number_wizard.xml
odoo12_addon_easy_my_coop_recompute_coop_number-12.0.1.0.0.99.dev1.dist-info/METADATA
odoo12_addon_easy_my_coop_recompute_coop_number-12.0.1.0.0.99.dev1.dist-info/WHEEL
odoo12_addon_easy_my_coop_recompute_coop_number-12.0.1.0.0.99.dev1.dist-info/top_level.txt
odoo12_addon_easy_my_coop_recompute_coop_number-12.0.1.0.0.99.dev1.dist-info/RECORD
