Metadata-Version: 2.1
Name: odoo12-addon-easy-my-coop-recompute-coop-number
Version: 12.0.1.0.0.99.dev1
Summary: Easy My Coop Recompute Coop Number
Home-page: https://coopiteasy.be
Author: Houssine BAKKALI <houssine@coopiteasy.be>
License: UNKNOWN
Platform: UNKNOWN
Classifier: Programming Language :: Python
Classifier: Framework :: Odoo
Requires-Python: >=3.5
Requires-Dist: odoo12-addon-easy-my-coop
Requires-Dist: odoo (<12.1dev,>=12.0a)
